omadb/OMARestAPI.py
omadb/__init__.py
omadb-2.2.4.dist-info/COPYING
omadb-2.2.4.dist-info/COPYING.LESSER
omadb-2.2.4.dist-info/METADATA
omadb-2.2.4.dist-info/WHEEL
omadb-2.2.4.dist-info/top_level.txt
omadb-2.2.4.dist-info/RECORD
